understory/owner/__init__.py
understory/owner/templates/__init__.py
understory/owner/templates/claim.html
understory/owner/templates/claimed.html
understory/owner/templates/index.html
understory/owner/templates/signin.html
understory/owner/templates/signout.html
understory/owner/templates/unauthorized.html
understory_owner-0.0.35.dist-info/LICENSE
understory_owner-0.0.35.dist-info/WHEEL
understory_owner-0.0.35.dist-info/METADATA
understory_owner-0.0.35.dist-info/RECORD
