Metadata-Version: 2.1
Name: understory-owner
Version: 0.0.35
Summary: 
License: AGPL-3.0-or-later
Author: Angelo Gladding
Author-email: angelo@ragt.ag
Requires-Python: >=3.9,<3.11
Classifier: License :: OSI Approved :: GNU Affero General Public License v3 or later (AGPLv3+)
Classifier: Programming Language :: Python :: 3
Classifier: Programming Language :: Python :: 3.9
Requires-Dist: pycryptodome (>=3.14.1,<4.0.0)
Requires-Dist: understory (>=0.0,<0.1)
